[
  [
    {
      "type": "阶段1：Web 基础",
      "img": "https://dn-simplecloud.shiyanlou.com/1548126810319.png?imageView2/2/h/150/q/100",
      "title": "HTML 基础课程",
      "follow": "8464"
    },
    {
      "type": "阶段1：Web 基础",
      "img": "https://dn-simplecloud.shiyanlou.com/courses/uid214893-20200320-1584668924916?imageView2/2/h/150/q/100",
      "title": "CSS3 简明教程",
      "follow": "3691"
    },
    {
      "type": "阶段1：Web 基础",
      "img": "https://dn-simplecloud.shiyanlou.com/1548916517593.png?imageView2/2/h/150/q/100",
      "title": "JavaScript 基础入门",
      "follow": "8767"
    },
    {
      "type": "阶段1：Web 基础",
      "img": "https://dn-simplecloud.shiyanlou.com/courses/uid214893-20200320-1584668936196?imageView2/2/h/150/q/100",
      "title": "HTML5 简明教程",
      "follow": "25610"
    },
    {
      "type": "阶段1：Web 基础",
      "img": "https://dn-simplecloud.shiyanlou.com/course/1551876285807_【1246】-【CSS3基础教程】.png?imageView2/2/h/150/q/100",
      "title": "CSS3 基础入门",
      "follow": "710"
    }
  ],
  [
    {
      "type": "阶段2：框架基础",
      "img": "https://dn-simplecloud.shiyanlou.com/course/1554280673829_【1262】-【Vue基础入门】.png?imageView2/2/h/150/q/100",
      "title": "Vue.js 基础入门",
      "follow": "3455"
    },
    {
      "type": "阶段2：框架基础",
      "img": "https://dn-simplecloud.shiyanlou.com/course/1554347205758_【1275】-【React基础入门】.png?imageView2/2/h/150/q/100",
      "title": "React 基础入门",
      "follow": "855"
    },
    {
      "type": "阶段2：框架基础",
      "img": "https://dn-simplecloud.shiyanlou.com/ncn50.jpg?imageView2/2/h/150/q/100",
      "title": "Bootstrap 3 基础入门",
      "follow": "10242"
    },
    {
      "type": "阶段2：框架基础",
      "img": "https://dn-simplecloud.shiyanlou.com/1552023199704.png?imageView2/2/h/150/q/100",
      "title": "Node.js 基础入门",
      "follow": "11857"
    }
  ],
  [
    {
      "type": "阶段3：基础项目",
      "img": "https://dn-simplecloud.shiyanlou.com/1485139664639.png?imageView2/2/h/150/q/100",
      "title": "纯 CSS 打造网页版「大白」",
      "follow": "8548"
    },
    {
      "type": "阶段3：基础项目",
      "img": "https://dn-simplecloud.shiyanlou.com/course/1542591908670_【62】-【网页版2048】.png?imageView2/2/h/150/q/100",
      "title": "HTML5 实现 2048 游戏",
      "follow": "3448"
    },
    {
      "type": "阶段3：基础项目",
      "img": "https://dn-simplecloud.shiyanlou.com/1517277170996.png?imageView2/2/h/150/q/100",
      "title": "网页版拼图游戏",
      "follow": "8093"
    },
    {
      "type": "阶段3：基础项目",
      "img": "https://dn-simplecloud.shiyanlou.com/course/1542592334446_【306】-【网页版别踩白块游戏】.png?imageView2/2/h/150/q/100",
      "title": "网页版别踩白块游戏",
      "follow": "7076"
    },
    {
      "type": "阶段3：基础项目",
      "img": "https://dn-simplecloud.shiyanlou.com/ncn80.jpg?imageView2/2/h/150/q/100",
      "title": "jQuery 实现图片轮播效果",
      "follow": "1094"
    },
    {
      "type": "阶段3：基础项目",
      "img": "https://dn-simplecloud.shiyanlou.com/1517277137475.png?imageView2/2/h/150/q/100",
      "title": "HTML5 实现刮刮乐游戏",
      "follow": "2513"
    },
    {
      "type": "阶段3：基础项目",
      "img": "https://dn-simplecloud.shiyanlou.com/1523250791024.png?imageView2/2/h/150/q/100",
      "title": "基于 CSS3 实现抽奖大转盘",
      "follow": "885"
    },
    {
      "type": "阶段3：基础项目",
      "img": "https://dn-simplecloud.shiyanlou.com/1528889651589.png?imageView2/2/h/150/q/100",
      "title": "HTML5 Canvas 实现放大镜效果",
      "follow": "693"
    },
    {
      "type": "阶段3：基础项目",
      "img": "https://dn-simplecloud.shiyanlou.com/course/1542594091116_【666】-【jQuery在购物车中的使用】.png?imageView2/2/h/150/q/100",
      "title": "jQuery 实现购物车功能",
      "follow": "1638"
    },
    {
      "type": "阶段3：基础项目",
      "img": "https://dn-simplecloud.shiyanlou.com/1454249787183.png?imageView2/2/h/150/q/100",
      "title": "CSS 实现红包模糊效果",
      "follow": "1245"
    },
    {
      "type": "阶段3：基础项目",
      "img": "https://dn-simplecloud.shiyanlou.com/ncn361.jpg?imageView2/2/h/150/q/100",
      "title": "HTML5 Canvas 实现小游戏",
      "follow": "11007"
    },
    {
      "type": "阶段3：基础项目",
      "img": "https://dn-simplecloud.shiyanlou.com/ncn67.jpg?imageView2/2/h/150/q/100",
      "title": "jQuery 实现图片瀑布流效果",
      "follow": "1013"
    },
    {
      "type": "阶段3：基础项目",
      "img": "https://dn-simplecloud.shiyanlou.com/ncn363.jpg?imageView2/2/h/150/q/100",
      "title": "基于 HTML5 实现本地图片裁剪",
      "follow": "6929"
    },
    {
      "type": "阶段3：基础项目",
      "img": "https://dn-simplecloud.shiyanlou.com/course/1558490173139_【1326】-【JavaScript实现js代码压缩成圣诞树】.png?imageView2/2/h/150/q/100",
      "title": "JavaScript 实现代码压缩成圣诞树",
      "follow": "59"
    }
  ],
  [
    {
      "type": "阶段4：进阶项目",
      "img": "https://dn-simplecloud.shiyanlou.com/1485139144548.png?imageView2/2/h/150/q/100",
      "title": "基于 Bootstrap 和 PHP 实现有道翻译【下线】",
      "follow": "830"
    },
    {
      "type": "阶段4：进阶项目",
      "img": "https://dn-simplecloud.shiyanlou.com/1446534523247.png?imageView2/2/h/150/q/100",
      "title": "HTML 实现 Markdown 编辑器",
      "follow": "753"
    },
    {
      "type": "阶段4：进阶项目",
      "img": "https://dn-simplecloud.shiyanlou.com/1500519319376.png?imageView2/2/h/150/q/100",
      "title": "React+Express+MongoDB 仿网易云音乐",
      "follow": "949"
    },
    {
      "type": "阶段4：进阶项目",
      "img": "https://dn-simplecloud.shiyanlou.com/1501207033286.png?imageView2/2/h/150/q/100",
      "title": "Vue.js 实现富文本编辑器",
      "follow": "1092"
    },
    {
      "type": "阶段4：进阶项目",
      "img": "https://dn-simplecloud.shiyanlou.com/course/1557453810588_【1310】-【React全家桶实现销售管理系统】.png?imageView2/2/h/150/q/100",
      "title": "React 全家桶实现销售管理系统",
      "follow": "122"
    }
  ]
]